pyroSAR/__init__.py
pyroSAR/ancillary.py
pyroSAR/auxdata.py
pyroSAR/config.py
pyroSAR/datacube_util.py
pyroSAR/drivers.py
pyroSAR/examine.py
pyroSAR/patterns.py
pyroSAR/xml_util.py
pyroSAR/ERS/__init__.py
pyroSAR/ERS/auxil.py
pyroSAR/ERS/mapping.py
pyroSAR/ERS/data/erspasses.db
pyroSAR/S1/__init__.py
pyroSAR/S1/auxil.py
pyroSAR/S1/linesimplify.py
pyroSAR/S1/polysimplify.py
pyroSAR/gamma/__init__.py
pyroSAR/gamma/api.py
pyroSAR/gamma/auxil.py
pyroSAR/gamma/dem.py
pyroSAR/gamma/error.py
pyroSAR/gamma/parser.py
pyroSAR/gamma/parser_demo.py
pyroSAR/gamma/util.py
pyroSAR/install/download_egm96_15.gtx.sh
pyroSAR/install/download_testdata.sh
pyroSAR/install/install_deps.sh
pyroSAR/snap/__init__.py
pyroSAR/snap/auxil.py
pyroSAR/snap/util.py
pyroSAR/snap/data/collect_suffices.py
pyroSAR/snap/data/snap.auxdata.properties
pyroSAR/snap/data/snap.suffices.properties
pyroSAR/snap/recipes/base.xml
pyroSAR/snap/recipes/blank.xml
pyrosar-0.33.3.dist-info/licenses/LICENSE.txt
pyrosar-0.33.3.dist-info/METADATA
pyrosar-0.33.3.dist-info/WHEEL
pyrosar-0.33.3.dist-info/top_level.txt
pyrosar-0.33.3.dist-info/RECORD
