Metadata-Version: 2.4
Name: pyroSAR
Version: 0.33.3
Summary: a framework for large-scale SAR satellite data processing
Maintainer-email: John Truckenbrodt <john.truckenbrodt@dlr.de>
License: # Copyright (c) 2014-2026, the pyroSAR Developers.
Project-URL: repository, https://github.com/johntruckenbrodt/pyroSAR
Project-URL: documentation, https://pyrosar.readthedocs.io/en/latest/
Classifier: License :: OSI Approved :: MIT License
Classifier: Operating System :: Microsoft :: Windows
Classifier: Operating System :: POSIX :: Linux
Classifier: Programming Language :: Python :: 3
Requires-Python: >=3.10
License-File: LICENSE.txt
Requires-Dist: geoalchemy2<0.14.0
Requires-Dist: lxml
Requires-Dist: numpy
Requires-Dist: packaging
Requires-Dist: pillow
Requires-Dist: progressbar2
Requires-Dist: psycopg2
Requires-Dist: pyyaml
Requires-Dist: requests
Requires-Dist: shapely
Requires-Dist: spatialist>=0.16.2
Requires-Dist: sqlalchemy-utils<0.42,>=0.37
Requires-Dist: sqlalchemy<2.0,>=1.4
Provides-Extra: test
Requires-Dist: pytest; extra == "test"
Provides-Extra: docs
Requires-Dist: sphinx; extra == "docs"
Requires-Dist: sphinx_rtd_theme; extra == "docs"
Requires-Dist: sphinxcontrib-bibtex; extra == "docs"
Requires-Dist: sphinxcontrib-svg2pdfconverter; extra == "docs"
Requires-Dist: cairosvg; extra == "docs"
Dynamic: license-file
